serl_sprl/__init__.py
serl_sprl/sets.py
serl_sprl/benchmarking/__init__.py
serl_sprl/benchmarking/base.py
serl_sprl/benchmarking/environments.py
serl_sprl/envs/__init__.py
serl_sprl/envs/configs.py
serl_sprl/envs/safe_region.py
serl_sprl/envs/pendulum/__init__.py
serl_sprl/envs/pendulum/pendulum.py
serl_sprl/envs/quadrotor/__init__.py
serl_sprl/envs/quadrotor/quadrotor_coupled_dynamics.py
serl_sprl/envs/seeker/__init__.py
serl_sprl/projection/__init__.py
serl_sprl/projection/projection_helpers.py
serl_sprl/projection/projection_wrappers.py
serl_sprl/sb3_contrib/__init__.py
serl_sprl/sb3_contrib/algorithm_configs.py
serl_sprl-0.1.0.dist-info/METADATA
serl_sprl-0.1.0.dist-info/WHEEL
serl_sprl-0.1.0.dist-info/top_level.txt
serl_sprl-0.1.0.dist-info/RECORD
