Metadata-Version: 2.4
Name: serl-sprl
Version: 0.1.0
Summary: Add your description here
Requires-Python: >=3.10
Requires-Dist: cvxpy>=1.7.2
Requires-Dist: pydantic>=2.11.9
Requires-Dist: pygame>=2.6.1
Requires-Dist: scipy>=1.15.3
Requires-Dist: stable-baselines3>=2.7.0
Requires-Dist: torch>=2.8.0
